odoo/addons/helpdesk_portal_priority/README.rst
odoo/addons/helpdesk_portal_priority/__init__.py
odoo/addons/helpdesk_portal_priority/__manifest__.py
odoo/addons/helpdesk_portal_priority/controllers/__init__.py
odoo/addons/helpdesk_portal_priority/controllers/main.py
odoo/addons/helpdesk_portal_priority/i18n/helpdesk_portal_priority.pot
odoo/addons/helpdesk_portal_priority/i18n/it.po
odoo/addons/helpdesk_portal_priority/i18n/pt_BR.po
odoo/addons/helpdesk_portal_priority/readme/CONTRIBUTORS.md
odoo/addons/helpdesk_portal_priority/readme/DESCRIPTION.md
odoo/addons/helpdesk_portal_priority/readme/USAGE.md
odoo/addons/helpdesk_portal_priority/static/description/icon.png
odoo/addons/helpdesk_portal_priority/static/description/icon.svg
odoo/addons/helpdesk_portal_priority/static/description/index.html
odoo/addons/helpdesk_portal_priority/views/helpdesk_ticket_templates.xml
odoo_addon_helpdesk_portal_priority-16.0.1.0.0.7.dist-info/METADATA
odoo_addon_helpdesk_portal_priority-16.0.1.0.0.7.dist-info/WHEEL
odoo_addon_helpdesk_portal_priority-16.0.1.0.0.7.dist-info/top_level.txt
odoo_addon_helpdesk_portal_priority-16.0.1.0.0.7.dist-info/RECORD
