Metadata-Version: 2.1
Name: odoo-addon-helpdesk_portal_priority
Version: 16.0.1.0.0.7
Summary: Helpdesk Portal Priority
Home-page: https://github.com/OCA/helpdesk
Author: Lansana Barry Sow, APSL-Nagarro, Odoo Community Association (OCA)
Author-email: support@odoo-community.org
License: AGPL-3
Classifier: Programming Language :: Python
Classifier: Framework :: Odoo
Classifier: Framework :: Odoo :: 16.0
Classifier: License :: OSI Approved :: GNU Affero General Public License v3
Requires-Python: >=3.10
Requires-Dist: odoo-addon-helpdesk-mgmt<16.1dev,>=16.0dev
Requires-Dist: odoo<16.1dev,>=16.0a
